pymcp/__init__.py
pymcp/mixin.py
pymcp/server.py
pymcp/data_model/__init__.py
pymcp/data_model/response_models.py
pymcp_template-0.2.0.dist-info/METADATA
pymcp_template-0.2.0.dist-info/WHEEL
pymcp_template-0.2.0.dist-info/entry_points.txt
pymcp_template-0.2.0.dist-info/licenses/LICENSE
pymcp_template-0.2.0.dist-info/RECORD
