Metadata-Version: 2.4
Name: pymcp-template
Version: 0.2.0
Summary: A template for developing MCP servers in Python
Author-email: Anirban Basu <anirbanbasu@users.noreply.github.com>
License-Expression: MIT
License-File: LICENSE
Keywords: example,mcp-server,model-context-protocol-server,python3,server
Classifier: Development Status :: 4 - Beta
Classifier: Intended Audience :: Developers
Classifier: License :: OSI Approved :: MIT License
Classifier: Programming Language :: Python :: 3
Classifier: Programming Language :: Python :: 3.12
Requires-Python: >=3.12
Requires-Dist: ddgs>=9.5.4
Requires-Dist: environs>=14.3.0
Requires-Dist: fastmcp
